addressbook/AddressBook.py
addressbook/__init__.py
gui/__init__.py
gui/gui.py
addressbook_ccsss-0.0.4.dist-info/METADATA
addressbook_ccsss-0.0.4.dist-info/WHEEL
addressbook_ccsss-0.0.4.dist-info/entry_points.txt
addressbook_ccsss-0.0.4.dist-info/top_level.txt
addressbook_ccsss-0.0.4.dist-info/RECORD
